ursadb/terminal.py
ursadb/ursaclient.py
ursadb-1.0.data/scripts/ursaclient
ursadb-1.0.dist-info/LICENSE
ursadb-1.0.dist-info/METADATA
ursadb-1.0.dist-info/WHEEL
ursadb-1.0.dist-info/top_level.txt
ursadb-1.0.dist-info/RECORD
